xylo/__init__.py
xylo/api.py
xylo/bin/xylo.exe
xylo_injector-1.0.0.dist-info/METADATA
xylo_injector-1.0.0.dist-info/WHEEL
xylo_injector-1.0.0.dist-info/top_level.txt
xylo_injector-1.0.0.dist-info/RECORD
