Metadata-Version: 2.4
Name: xylo_injector
Version: 1.0.0
Summary: Xylo Dll injector
Home-page: https://github.com/xqrto/G4mH1x/tree/main/WtC/Type=Injector/xylo
Author: xqrto
License: MIT
Classifier: Programming Language :: Python :: 3
Classifier: Operating System :: Microsoft :: Windows
Requires-Python: >=3.8
